CHANGELOG.rst
LICENSE
expression_filter/__init__.py
expression_filter/bypass.py
django_expression_filter-0.0.1.dist-info/LICENSE
django_expression_filter-0.0.1.dist-info/WHEEL
django_expression_filter-0.0.1.dist-info/METADATA
django_expression_filter-0.0.1.dist-info/RECORD
