Metadata-Version: 2.1
Name: django-expression-filter
Version: 0.0.1
Summary: A class for Django filters to allow direct filtering on expressions, as you would normally do with annotations, so the annotation does not need to happen.
Home-page: https://github.com/hamstap85/django-expression-filter/
License: ISC
Keywords: django,filter,annotation,bypass,performance
Author: Hameed Gifford
Author-email: giff.h92@gmail.com
Requires-Python: >=3.6.2,<4
Classifier: Development Status :: 2 - Pre-Alpha
Classifier: Framework :: Django
Classifier: Framework :: Django :: 2.2
Classifier: Framework :: Django :: 3.0
Classifier: Framework :: Django :: 3.1
Classifier: Framework :: Django :: 3.2
Classifier: Intended Audience :: Developers
Classifier: License :: OSI Approved
Classifier: License :: OSI Approved :: ISC License (ISCL)
Classifier: Operating System :: OS Independent
Classifier: Programming Language :: Python
Classifier: Programming Language :: Python :: 3
Classifier: Programming Language :: Python :: 3 :: Only
Classifier: Programming Language :: Python :: 3.6
Classifier: Programming Language :: Python :: 3.7
Classifier: Programming Language :: Python :: 3.8
Classifier: Programming Language :: Python :: 3.9
Classifier: Topic :: Software Development :: Libraries :: Python Modules
Requires-Dist: Django (>=2.2,<4)
Project-URL: Repository, https://github.com/hamstap85/django-expression-filter/
